GrowCloneGo/__init__.py
GrowCloneGo/__main__.py
GrowCloneGo/cli.py
GrowCloneGo/core.py
growclonego-0.1.1.dist-info/licenses/LICENSE
growclonego-0.1.1.dist-info/METADATA
growclonego-0.1.1.dist-info/WHEEL
growclonego-0.1.1.dist-info/entry_points.txt
growclonego-0.1.1.dist-info/top_level.txt
growclonego-0.1.1.dist-info/RECORD
